setup.py
hello_python_package/__init__.py
hello_python_package/hello.py
hello_python_package.egg-info/PKG-INFO
hello_python_package.egg-info/SOURCES.txt
hello_python_package.egg-info/dependency_links.txt
hello_python_package.egg-info/not-zip-safe
hello_python_package.egg-info/top_level.txt