Metadata-Version: 1.0
Name: hello-python-package
Version: 0.2
Summary: Test Hello World package
Home-page: http://pypi.python.org/pypi/hello_python_package/0.1
Author: Daniel Keighley
Author-email: daniel.keighley@wpengine.com
License: WP
Platform: UNKNOWN
